django_include_htmx/__init__.py
django_include_htmx/static/js/htmx/htmx.js
django_include_htmx/static/js/htmx/htmx.min.js
django_include_htmx-0.1.0.dist-info/METADATA
django_include_htmx-0.1.0.dist-info/WHEEL
django_include_htmx-0.1.0.dist-info/top_level.txt
django_include_htmx-0.1.0.dist-info/RECORD
