Metadata-Version: 2.2
Name: django-include-htmx
Version: 0.1.0
Summary: Add your description here
Requires-Python: >=3.10
Requires-Dist: django>=3.2
